[
  {
    "listingReference": "example_listing_000001",
    "alias": "the_big_house",
    "type": "house",
    "kind": "shared_room",
    "description": "Historical beach house.\n Welcome to a beautiful mansion by the beach where you will have a private and cozy room",
    "address": "C. de Montalbán, 1, Retiro, 28014 Madrid, Spain",
    "currencyCode": "EUR",
    "pricingType": "monthly",
    "monthlyPrices": [
      {
        "month": "1",
        "price": 80000
      },
      {
        "month": "2",
        "price": 80000
      },
      {
        "month": "3",
        "price": 80000
      },
      {
        "month": "4",
        "price": 85000
      },
      {
        "month": "5",
        "price": 85000
      },
      {
        "month": "6",
        "price": 95000
      },
      {
        "month": "7",
        "price": 100000
      },
      {
        "month": "8",
        "price": 120000
      },
      {
        "month": "9",
        "price": 120000
      },
      {
        "month": "10",
        "price": 115000
      },
      {
        "month": "11",
        "price": 95000
      },
      {
        "month": "12",
        "price": 90000
      }
    ],
    "blockedPeriods": [
      {
        "startDate": "2025-12-01",
        "endDate": "2025-12-31"
      },
      {
        "startDate": "2026-07-01",
        "endDate": "2026-09-30"
      }
    ],
    "strictRentalPeriods": [
    {
      "price": 100000,
      "startDate": "2026-01-01",
      "endDate": "2026-12-01",
      "moveInEndDate": "2026-02-01"
    }
  ],
    "costs": {
      "security-deposit": {
        "value": 80000,
        "payableBy": "tenant",
        "payableAt": "move-in",
        "required": true,
        "refundable": true,
        "isEstimated": false
      },
      "administration-fee": {
        "value": 25000,
        "payableBy": "tenant",
        "payableAt": "move-in",
        "required": true,
        "refundable": false,
        "isEstimated": false
      },
      "electricity-bill": {
        "value": 1000,
        "payableBy": "tenant",
        "payableAt": "monthly",
        "required": true,
        "refundable": false,
        "isEstimated": true
      },
      "other-additional-costs": {
        "value": 10000,
        "payableBy": "tenant",
        "payableAt": "move-out",
        "required": false,
        "refundable": false,
        "isEstimated": false
      }
    },
    "minimumStayMonths": 1,
    "maximumStayMonths": 12,
    "moveInWindow": 15,
    "images": [
      "https://your-domain.com/images/prop-123456-1.jpg",
      "https://your-domain.com/images/prop-123456-2.jpg",
      "https://your-domain.com/images/prop-123456-3.jpg"
    ],
    "listingUrl": "https://your-domain.com/listings/PROP-123456",
    "minAge": 18,
    "maxAge": 35,
    "facilities": {
      "totalSize": 120,
      "bedroomSize": 14,
      "currentOccupancy": 1,
      "freePlaces": 3,
      "allergyFriendly": true,
      "housematesGender": "shared_w_girls",
      "registrationPossible": true,
      "tenantStatus": "working",
      "bedroomCount": 4,
      "bedroomFurnished": true,
      "bedroomLock": true,
      "balconyTerrace": "private",
      "basement": "shared",
      "bathroom": "shared_w_boys",
      "garden": "private",
      "kitchen": "shared",
      "livingRoom": "shared",
      "parking": "shared",
      "toilet": "shared",
      "kitchenware": "shared",
      "wheelchairAccessible": true,
      "ac": true,
      "bed": true,
      "closet": true,
      "desk": true,
      "dishwasher": false,
      "dryer": true,
      "flooring": "carpet",
      "internet": true,
      "livingRoomFurnished": true,
      "tv": true,
      "washingMachine": true,
      "wifi": true,
      "animalAllowed": "yes",
      "cleaningCommon": false,
      "cleaningPrivate": false,
      "playMusic": "discussable",
      "smokingAllowed": "outside_only",
      "preferredGender": "female",
      "couplesAllowed": true,
      "heating": "central"
    },
    "registrationNumber":"ESREG2026ALQ000000123456789VIV00000000098765432100000"
  },
  {
    "listingReference": "example_listing_00002",
    "registrationNumber":"ESREG2026ALQ000000123456789VIV00000000098765432102222",
    "alias": "the_small_house",
    "type": "house",
    "kind": "shared_room",
    "description": "Historical beach house.\n Welcome to a beautiful mansion by the beach where you will have a private and cozy room",
    "address": "Carrer de Montcada, 25, Ciutat Vella, 08003 Barcelona, Spain",
    "currencyCode": "EUR",
    "pricingType": "monthly",
    "monthlyPrices": [
      {
        "month": "1",
        "price": 80000
      },
      {
        "month": "2",
        "price": 80000
      },
      {
        "month": "3",
        "price": 80000
      },
      {
        "month": "4",
        "price": 85000
      },
      {
        "month": "5",
        "price": 85000
      },
      {
        "month": "6",
        "price": 95000
      },
      {
        "month": "7",
        "price": 100000
      },
      {
        "month": "8",
        "price": 120000
      },
      {
        "month": "9",
        "price": 120000
      },
      {
        "month": "10",
        "price": 115000
      },
      {
        "month": "11",
        "price": 95000
      },
      {
        "month": "12",
        "price": 90000
      }
    ],
    "blockedPeriods": [
      {
        "startDate": "2025-12-01",
        "endDate": "2019-12-31"
      },
      {
        "startDate": "2026-07-01",
        "endDate": "2019-09-30"
      }
    ],
    "costs": {
      "security-deposit": {
        "value": 80000,
        "payableBy": "tenant",
        "payableAt": "move-in",
        "required": true,
        "refundable": true,
        "isEstimated": false
      },
      "administration-fee": {
        "value": 25000,
        "payableBy": "tenant",
        "payableAt": "move-in",
        "required": true,
        "refundable": false,
        "isEstimated": false
      },
      "electricity-bill": {
        "value": 1000,
        "payableBy": "tenant",
        "payableAt": "weekly",
        "required": true,
        "refundable": false,
        "isEstimated": true
      },
       "cleaning-fee": {
        "value": 50000,
        "payableBy": "tenant",
        "payableAt": "bi-weekly",
        "required": true,
        "refundable": false,
        "isEstimated": true
      },
     "other-additional-costs": {
        "value": 70000,
        "payableBy": "tenant",
        "payableAt": "move-out",
        "required": true,
        "refundable": false,
        "isEstimated": false
      }
    },
    "minimumStayMonths": 1,
    "maximumStayMonths": 12,
    "moveInWindow": 15,
    "images": [
      "https://fastly.picsum.photos/id/110/200/300.jpg?hmac=IMeVMiaNHiAeyVJRyiLHVnYMW0UpSBDkkUtSO1gIidQ",
      "https://fastly.picsum.photos/id/603/200/300.jpg?hmac=7egn04uCRc_cYvj1RxmKD8W1ySpBC3Ut8GFrvACb4x0",
      "https://fastly.picsum.photos/id/238/200/300.jpg?hmac=WF3u-tnO4aoQvz_F9p7zS0Dr5LwGx74tPabQf7EjHkw"
    ],
    "listingUrl": "https://your-domain.com/listings/PROP-123456",
    "minAge": 18,
    "maxAge": 35,
    "payoutMethodName": "Bank account 3",
    "facilities": {
      "totalSize": 120,
      "bedroomSize": 14,
      "currentOccupancy": 1,
      "freePlaces": 3,
      "allergyFriendly": true,
      "housematesGender": "shared_w_girls",
      "registrationPossible": true,
      "tenantStatus": "working",
      "bedroomCount": 4,
      "bedroomFurnished": true,
      "bedroomLock": true,
      "balconyTerrace": "private",
      "basement": "shared",
      "bathroom": "shared_w_boys",
      "garden": "private",
      "kitchen": "shared",
      "livingRoom": "shared",
      "parking": "shared",
      "toilet": "shared",
      "kitchenware": "shared",
      "wheelchairAccessible": true,
      "ac": true,
      "bed": true,
      "closet": true,
      "desk": true,
      "dishwasher": false,
      "dryer": true,
      "flooring": "carpet",
      "internet": true,
      "livingRoomFurnished": true,
      "tv": true,
      "washingMachine": true,
      "wifi": true,
      "animalAllowed": "yes",
      "cleaningCommon": false,
      "cleaningPrivate": false,
      "playMusic": "discussable",
      "smokingAllowed": "outside_only",
      "preferredGender": "female",
      "couplesAllowed": true,
      "heating": "central"
    }
  },
  {
    "listingReference": "1549123",
    "type": "apartment",
    "kind": "private_room",
    "address": "Plaza Mayor, Centro, Madrid, Spain",
    "description": "Esta es una descripción de prueba con más de 50 caracteres para pasar validación.",
    "pricingType": "flat",
    "flatPrice": 120000,
    "currencyCode": "EUR",
    "images": [],
    "blockedPeriods": [
      {
        "startDate": "2025-08-01",
        "endDate": "2025-08-11"
      },
      {
        "startDate": "2025-08-15",
        "endDate": "2025-08-22"
      },
      {
        "startDate": "2025-09-22",
        "endDate": "2025-10-21"
      },
      {
        "startDate": "2025-10-25",
        "endDate": "2025-12-09"
      },
      {
        "startDate": "2026-02-01",
        "endDate": "2026-04-01"
      }
    ],
    "lastUpdated": "2025-12-16T08:21:00.736Z"
  },
  {
    "listingReference": "spanishListingWithNoNRA",
    "type": "apartment",
    "kind": "private_room",
    "address": "Plaza Mayor, Centro, Madrid, Spain",
    "description": "Esta es una descripción de prueba con más de 50 caracteres para pasar validación.",
    "pricingType": "flat",
    "flatPrice": 120000,
    "currencyCode": "EUR",
    "images": [],
    "blockedPeriods": [
      {
        "startDate": "2025-08-01",
        "endDate": "2025-08-11"
      },
      {
        "startDate": "2025-08-15",
        "endDate": "2025-08-22"
      },
      {
        "startDate": "2025-09-22",
        "endDate": "2025-10-21"
      },
      {
        "startDate": "2025-10-25",
        "endDate": "2025-12-09"
      },
      {
        "startDate": "2026-12-01",
        "endDate": "2026-12-28"
      }
    ]
  }
]
